mydotenv/.env
mydotenv/__init__.py
mydotenv/__init__.pyi
mydotenv/cli.py
mydotenv/config.py
mydotenv/symlink.py
mydotenv-0.2.6.dist-info/licenses/LICENSE
mydotenv-0.2.6.dist-info/METADATA
mydotenv-0.2.6.dist-info/WHEEL
mydotenv-0.2.6.dist-info/entry_points.txt
mydotenv-0.2.6.dist-info/top_level.txt
mydotenv-0.2.6.dist-info/RECORD
